[
  {
    "id": "INJ001",
    "athleteId": "ATH001",
    "athleteName": "James Wilson",
    "injuryType": "Hamstring Strain",
    "severity": "Grade 2",
    "location": "Left Leg",
    "dateOccurred": "2024-11-15",
    "dateRecovered": "2025-01-05",
    "daysOut": 51,
    "mechanism": "Sprint",
    "context": "During match vs Blue Eagles",
    "recurrence": false,
    "treatmentPlan": "Rest, physiotherapy, gradual return to training",
    "rehabilitationStatus": "Completed",
    "notes": "Full recovery achieved, monitoring workload during return to play"
  },
  {
    "id": "INJ002",
    "athleteId": "ATH003",
    "athleteName": "Carlos Mendez",
    "injuryType": "Ankle Sprain",
    "severity": "Grade 1",
    "location": "Right Ankle",
    "dateOccurred": "2025-02-03",
    "dateRecovered": "2025-02-17",
    "daysOut": 14,
    "mechanism": "Tackle",
    "context": "Training session",
    "recurrence": false,
    "treatmentPlan": "RICE protocol, ankle stability exercises",
    "rehabilitationStatus": "Completed",
    "notes": "Responded well to treatment, no lingering issues"
  },
  {
    "id": "INJ003",
    "athleteId": "ATH002",
    "athleteName": "Sarah Johnson",
    "injuryType": "ACL Tear",
    "severity": "Complete Tear",
    "location": "Right Knee",
    "dateOccurred": "2024-09-28",
    "dateRecovered": "2025-04-15",
    "daysOut": 199,
    "mechanism": "Non-contact pivot",
    "context": "Match vs Green Sharks",
    "recurrence": false,
    "treatmentPlan": "Surgical reconstruction, extensive rehabilitation program",
    "rehabilitationStatus": "Completed",
    "notes": "Successful surgery, followed complete rehabilitation protocol"
  },
  {
    "id": "INJ004",
    "athleteId": "ATH005",
    "athleteName": "David Okonkwo",
    "injuryType": "Concussion",
    "severity": "Mild",
    "location": "Head",
    "dateOccurred": "2025-03-12",
    "dateRecovered": "2025-03-22",
    "daysOut": 10,
    "mechanism": "Head collision",
    "context": "Aerial challenge during match",
    "recurrence": false,
    "treatmentPlan": "Concussion protocol, gradual return to play",
    "rehabilitationStatus": "Completed",
    "notes": "Passed all cognitive tests before return to play"
  },
  {
    "id": "INJ005",
    "athleteId": "ATH007",
    "athleteName": "Lucas Kim",
    "injuryType": "Groin Strain",
    "severity": "Grade 1",
    "location": "Left Groin",
    "dateOccurred": "2025-01-20",
    "dateRecovered": "2025-02-03",
    "daysOut": 14,
    "mechanism": "Stretching for ball",
    "context": "Training session",
    "recurrence": true,
    "treatmentPlan": "Rest, physiotherapy, core strengthening",
    "rehabilitationStatus": "Completed",
    "notes": "History of similar injuries, implementing prevention program"
  },
  {
    "id": "INJ006",
    "athleteId": "ATH004",
    "athleteName": "Emma Chen",
    "injuryType": "Finger Fracture",
    "severity": "Simple Fracture",
    "location": "Right Index Finger",
    "dateOccurred": "2025-02-28",
    "dateRecovered": "2025-04-11",
    "daysOut": 42,
    "mechanism": "Ball impact",
    "context": "Goalkeeper training",
    "recurrence": false,
    "treatmentPlan": "Splint, protected training with special glove",
    "rehabilitationStatus": "Completed",
    "notes": "Healed well, no impact on performance post-recovery"
  },
  {
    "id": "INJ007",
    "athleteId": "ATH006",
    "athleteName": "Sophia Martinez",
    "injuryType": "Lower Back Pain",
    "severity": "Moderate",
    "location": "Lumbar Region",
    "dateOccurred": "2025-03-05",
    "dateRecovered": "2025-03-19",
    "daysOut": 14,
    "mechanism": "Overuse",
    "context": "Reported after intensive training block",
    "recurrence": true,
    "treatmentPlan": "Rest, manual therapy, core strengthening",
    "rehabilitationStatus": "Completed",
    "notes": "Ongoing management with specialized exercise program"
  },
  {
    "id": "INJ008",
    "athleteId": "ATH001",
    "athleteName": "James Wilson",
    "injuryType": "Quadriceps Contusion",
    "severity": "Moderate",
    "location": "Right Thigh",
    "dateOccurred": "2025-03-25",
    "dateRecovered": "2025-04-01",
    "daysOut": 7,
    "mechanism": "Direct impact",
    "context": "Knee collision during match",
    "recurrence": false,
    "treatmentPlan": "RICE protocol, progressive loading",
    "rehabilitationStatus": "Completed",
    "notes": "Minimal impact on performance after return"
  }
]
